openwrite/__init__.py
openwrite/cli.py
openwrite/gemini_multi.py
openwrite/gemini_single.py
openwrite/db/__init__.py
openwrite/db/base.py
openwrite/routes/admin.py
openwrite/routes/auth.py
openwrite/routes/blog.py
openwrite/routes/dashboard.py
openwrite/routes/federation.py
openwrite/routes/main.py
openwrite/routes/upload.py
openwrite/static/IBMPlexSans-Regular.ttf
openwrite/static/Merriweather.ttf
openwrite/static/avatar.png
openwrite/static/emoji.json
openwrite/static/favicon.ico
openwrite/static/favicon.png
openwrite/static/logo.png
openwrite/static/feed/.gitkeep
openwrite/static/feed/74.xml
openwrite/static/feed/a.xml
openwrite/static/feed/anim3sh1t.xml
openwrite/static/feed/b.xml
openwrite/static/feed/corrode.xml
openwrite/static/feed/dirtysanchez.xml
openwrite/static/feed/eikerammen.xml
openwrite/static/feed/fedi.xml
openwrite/static/feed/friskt.xml
openwrite/static/feed/gordi.xml
openwrite/static/feed/igilq.xml
openwrite/static/feed/io.xml
openwrite/static/feed/isyuricunha.xml
openwrite/static/feed/kenny.xml
openwrite/static/feed/m0bi.xml
openwrite/static/feed/main.xml
openwrite/static/feed/mywritese.xml
openwrite/static/feed/nay-thoughs.xml
openwrite/static/feed/nintendoflesz.xml
openwrite/static/feed/phronima.xml
openwrite/static/feed/ram.xml
openwrite/static/feed/samah.xml
openwrite/static/feed/themes-test.xml
openwrite/static/feed/totylkoja.xml
openwrite/static/feed/vegafjord.xml
openwrite/static/feed/vijayvaradharaj.xml
openwrite/static/script/chart.js
openwrite/static/script/highlight.min.js
openwrite/static/script/nativeEmoji.js
openwrite/static/script/openwrite.js
openwrite/static/script/papaparse.min.js
openwrite/static/script/showdown.min.js
openwrite/static/script/showdown.min.js.map
openwrite/static/script/site.compat.min.js
openwrite/static/script/site.min.js
openwrite/static/style/blog_design.css
openwrite/static/style/default.css
openwrite/static/style/hl.css
openwrite/static/style/nativeEmoji.min.css
openwrite/static/style/style.css
openwrite-0.15.0.dist-info/licenses/LICENSE
openwrite-0.15.0.dist-info/METADATA
openwrite-0.15.0.dist-info/WHEEL
openwrite-0.15.0.dist-info/entry_points.txt
openwrite-0.15.0.dist-info/top_level.txt
openwrite-0.15.0.dist-info/RECORD
