Metadata-Version: 2.4
Name: openwrite
Version: 0.15.0
License:                     GNU AFFERO GENERAL PUBLIC LICENSE
Project-URL: Homepage, https://openwrite.io
Project-URL: Source Code, https://codeberg.org/v0id1st/openwrite
Requires-Python: >=3.11
License-File: LICENSE
Requires-Dist: flask
Requires-Dist: python-dotenv
Requires-Dist: sqlalchemy
Requires-Dist: bcrypt
Requires-Dist: feedgen
Requires-Dist: Pillow
Requires-Dist: requests
Requires-Dist: bleach
Requires-Dist: flask-cors
Requires-Dist: PyMySQL
Requires-Dist: gunicorn
Requires-Dist: beautifulsoup4
Requires-Dist: cryptography
Requires-Dist: markdown
Requires-Dist: md2gemini
Requires-Dist: gmcapsule
Requires-Dist: user-agents
Requires-Dist: redis
Dynamic: license-file
